{  "JobId": "d9f3855c-43d1-4fcd-9fb7-032e231a1707",  
    "item": {    
        "id": 4,    
        "title": "Elgato Wave:3 - Microfone condensador USB e misturador digital para streaming, gravação, podcasting - Clipguard, Capacitive Mute, Plug & Play para PC / Mac",    
        "description": "Wave 3 é um microfone premium e uma solução de mixagem digital que funde a conveniência de plug and play com circuitos de grau de transmissão. Nunca mais se deve recortar graças à tecnologia proprietária anti-distorção. E combine todas as suas fontes de áudio, além de criar duas mixagens independentes - uma para você, outra para seu público - com o aplicativo Wave Link.",    
        "file_path": "https://octank-moderation.s3.amazonaws.com/1608317073450-elgato wave 3.jpg",    
        "status": "in review",    
        "published": false,    
        "createdAt": "2020-12-18T19:19:22.000Z",    
        "updatedAt": "2020-12-18T19:19:22.000Z"  
    },  
    "Bucket": "octank-moderation",  
    "Key": "1608317073450-elgato wave 3.jpg",  
    "Match": false,  
    "CategoryMatch": "Firearm"
}